setup.py
Matrixop/__init__.py
Matrixop/operations.py
Matrixop.egg-info/PKG-INFO
Matrixop.egg-info/SOURCES.txt
Matrixop.egg-info/dependency_links.txt
Matrixop.egg-info/not-zip-safe
Matrixop.egg-info/top_level.txt