Metadata-Version: 1.0
Name: Matrixop
Version: 0.1
Summary: Matrix operations
Home-page: UNKNOWN
Author: Tagne Nguifo Eric Hermann
Author-email: UNKNOWN
License: UNKNOWN
Platform: UNKNOWN
